tshistory_rest/__init__.py
tshistory_rest/app.py
tshistory_rest/blueprint.py
tshistory_rest/util.py
tshistory_rest-0.10.0.dist-info/METADATA
tshistory_rest-0.10.0.dist-info/WHEEL
tshistory_rest-0.10.0.dist-info/top_level.txt
tshistory_rest-0.10.0.dist-info/RECORD
