Metadata-Version: 2.1
Name: tshistory-rest
Version: 0.10.0
Summary: Timeseries histories http front
Home-page: https://hg.sr.ht/~pythonian/tshistory_rest
Author: Pythonian
Author-email: aurelien.campeas@pythonian.fr
License: UNKNOWN
Platform: UNKNOWN
Classifier: Development Status :: 4 - Beta
Classifier: Intended Audience :: Developers
Classifier: License :: OSI Approved :: GNU Lesser General Public License v3 (LGPLv3)
Classifier: Operating System :: OS Independent
Classifier: Programming Language :: Python :: 3
Classifier: Topic :: Database
Classifier: Topic :: Scientific/Engineering
Classifier: Topic :: Software Development :: Version Control
Requires-Dist: flask (<2.0)
Requires-Dist: jinja2 (<3.0)
Requires-Dist: flask-restx
Requires-Dist: tshistory (>=0.13.0)
Requires-Dist: requests
Requires-Dist: pytest-sa-pg
Requires-Dist: webtest
Requires-Dist: pandas
